CHANGES.txt
LICENSE.txt
MANIFEST.in
README.txt
setup.py
js/__init__.py
js.log4javascript.egg-info/PKG-INFO
js.log4javascript.egg-info/SOURCES.txt
js.log4javascript.egg-info/dependency_links.txt
js.log4javascript.egg-info/entry_points.txt
js.log4javascript.egg-info/namespace_packages.txt
js.log4javascript.egg-info/not-zip-safe
js.log4javascript.egg-info/requires.txt
js.log4javascript.egg-info/top_level.txt
js/log4javascript/__init__.py
js/log4javascript/test_log4javascript.txt
js/log4javascript/resources/log4javascript.js
js/log4javascript/resources/log4javascript_uncompressed.js