Metadata-Version: 1.0
Name: js.log4javascript
Version: 1.4.6
Summary: Fanstatic packaging of log4javascript
Home-page: UNKNOWN
Author: Fanstatic Developers
Author-email: fanstatic@googlegroups.com
License: BSD
Platform: UNKNOWN
